django_siruta-0.2.1.dist-info/licenses/LICENSE
siruta/__init__.py
siruta/__main__.py
siruta/cli.py
siruta/data.py
siruta/extras.py
siruta/forms.py
siruta/locale/ro/LC_MESSAGES/django.po
siruta/static/siruta/counties.js
siruta/templates/siruta/locality.html
siruta/templates/siruta/selectize_select.html
django_siruta-0.2.1.dist-info/METADATA
django_siruta-0.2.1.dist-info/WHEEL
django_siruta-0.2.1.dist-info/entry_points.txt
django_siruta-0.2.1.dist-info/top_level.txt
django_siruta-0.2.1.dist-info/RECORD
