Metadata-Version: 2.4
Name: django-siruta
Version: 0.2.1
Summary: A bunch of form fields and utilities for Romanian counties and localities using SIRUTA codes.
Author-email: Ionel Cristian Mărieș <contact@ionelmc.ro>
License-Expression: BSD-2-Clause
Project-URL: Sources, https://github.com/ionelmc/django-siruta
Project-URL: Documentation, https://django-siruta.readthedocs.io/
Project-URL: Changelog, https://django-siruta.readthedocs.io/en/latest/changelog.html
Project-URL: Issue Tracker, https://github.com/ionelmc/django-siruta/issues
Keywords: siruta,romania,romanian,counties,county
Classifier: Development Status :: 5 - Production/Stable
Classifier: Intended Audience :: Developers
Classifier: Operating System :: Unix
Classifier: Operating System :: POSIX
Classifier: Operating System :: Microsoft :: Windows
Classifier: Programming Language :: Python
Classifier: Programming Language :: Python :: 3
Classifier: Programming Language :: Python :: 3 :: Only
Classifier: Programming Language :: Python :: 3.9
Classifier: Programming Language :: Python :: 3.10
Classifier: Programming Language :: Python :: 3.11
Classifier: Programming Language :: Python :: 3.12
Classifier: Programming Language :: Python :: 3.13
Classifier: Programming Language :: Python :: 3.14
Classifier: Programming Language :: Python :: Implementation :: CPython
Classifier: Programming Language :: Python :: Implementation :: PyPy
Classifier: Topic :: Utilities
Requires-Python: >=3.9
License-File: LICENSE
Requires-Dist: unidecode
Requires-Dist: django
Provides-Extra: msgspec
Requires-Dist: msgspec; extra == "msgspec"
Dynamic: description
Dynamic: description-content-type
Dynamic: license-file
